docusign_maestro/__init__.py
docusign_maestro/apis/__init__.py
docusign_maestro/apis/workflow_instance_management_api.py
docusign_maestro/apis/workflow_management_api.py
docusign_maestro/apis/workflow_trigger_api.py
docusign_maestro/client/__init__.py
docusign_maestro/client/api_client.py
docusign_maestro/client/api_exception.py
docusign_maestro/client/api_response.py
docusign_maestro/client/configuration.py
docusign_maestro/client/auth/__init__.py
docusign_maestro/client/auth/oauth.py
docusign_maestro/models/__init__.py
docusign_maestro/models/access_token_response.py
docusign_maestro/models/access_token_token_types.py
docusign_maestro/models/account_id.py
docusign_maestro/models/aow_uuid.py
docusign_maestro/models/aow_uuid_string.py
docusign_maestro/models/cancel_response.py
docusign_maestro/models/create_or_update_workflow_definition_request_body.py
docusign_maestro/models/deploy_request.py
docusign_maestro/models/deploy_response.py
docusign_maestro/models/deploy_status.py
docusign_maestro/models/deployment_status.py
docusign_maestro/models/ds_do_until_step.py
docusign_maestro/models/ds_doc_gen_step.py
docusign_maestro/models/ds_doc_gen_step_input.py
docusign_maestro/models/ds_idv_step.py
docusign_maestro/models/ds_idv_step_input.py
docusign_maestro/models/ds_if_else_step.py
docusign_maestro/models/ds_loop_step.py
docusign_maestro/models/ds_parallel_step.py
docusign_maestro/models/ds_service_step.py
docusign_maestro/models/ds_sign_step.py
docusign_maestro/models/ds_sign_step_input.py
docusign_maestro/models/ds_step_id.py
docusign_maestro/models/ds_transformation_step.py
docusign_maestro/models/ds_web_forms_step.py
docusign_maestro/models/ds_web_forms_step_config.py
docusign_maestro/models/ds_workflow_boolean_expression.py
docusign_maestro/models/ds_workflow_comparison_expression.py
docusign_maestro/models/ds_workflow_comparison_operator_types.py
docusign_maestro/models/ds_workflow_concat_expression.py
docusign_maestro-3.0.0.dist-info/METADATA
docusign_maestro-3.0.0.dist-info/WHEEL
docusign_maestro-3.0.0.dist-info/top_level.txt
docusign_maestro-3.0.0.dist-info/RECORD
