Metadata-Version: 2.1
Name: docusign-maestro
Version: 3.0.0
Summary: ⚠️ Deprecated – Maestro is now available as part of the new IAM SDK: https://developers.docusign.com/docs/sdks/
Home-page: 
Author-email: devcenter@docusign.com
Keywords: Swagger,Maestro API
Requires-Dist: urllib3 (>=1.15)
Requires-Dist: six (>=1.8.0)
Requires-Dist: certifi (>=14.05.14)
Requires-Dist: python-dateutil (>=2.5.3)
Requires-Dist: setuptools (>=21.0.0)
Requires-Dist: PyJWT (>=2.0.0)
Requires-Dist: cryptography (>=2.5)
